robikalo/Types.py
robikalo/__init__.py
robikalo/client.py
robikalo/configs.py
robikalo/encryption.py
robikalo/exceptions.py
robikalo/fileIO.py
robikalo/filters.py
robikalo/rubino.py
robikalo/tools.py
robikalo-8.0.2.dist-info/LICENSE
robikalo-8.0.2.dist-info/METADATA
robikalo-8.0.2.dist-info/WHEEL
robikalo-8.0.2.dist-info/top_level.txt
robikalo-8.0.2.dist-info/RECORD
