Metadata-Version: 2.1
Name: robikalo
Version: 8.0.2
Summary: My first Python package
Author: Kazem Mirzaei
Author-email: k90mirzaei@gmail.com
Keywords: python,first package
Classifier: Development Status :: 3 - Alpha
Classifier: Intended Audience :: Education
Classifier: Programming Language :: Python :: 2
Classifier: Programming Language :: Python :: 3
License-File: LICENSE
Requires-Dist: requests
Requires-Dist: pycryptodome (==3.10.1)
Requires-Dist: urllib3
Requires-Dist: tqdm
Requires-Dist: aiohttp
Requires-Dist: rich
Requires-Dist: websocket-client
